[
  { "keyword": "postman login forced 2026 fix", "slug": "postman-login-forced-fix", "title": "Tired of Postman Forced Login? Test Your API Instantly Without Account", "problem_description": "User just wants to hit an endpoint but Postman requires a mandatory cloud login.", "how_to_solve": "OneClickAPI offers a zero-login interface. Paste URL, get response. No cloud bullshit." },
  { "keyword": "how to test api without postman bloat", "slug": "test-api-without-postman-bloat", "title": "Fastest Way to Test API Without Postman Bloat (0.8s Response)", "problem_description": "Postman takes too much RAM and time just for one GET request.", "how_to_solve": "OneClickAPI is a single-page tool that loads in milliseconds." },
  { "keyword": "online curl to python requests zero click", "slug": "curl-to-python-requests-instant", "title": "Instant cURL to Python Requests - Copy, Paste, Done", "problem_description": "Devs need to convert cURL to Python without complex menus.", "how_to_solve": "Paste cURL into OneClickAPI, get Python code instantly on the same screen." },
  { "keyword": "bypass cors for api testing online free", "slug": "bypass-cors-api-testing-online", "title": "Fix CORS Errors in Browser API Testing - Online Proxy Solver", "problem_description": "Frontend devs blocked by CORS when testing 3rd-party APIs from localhost.", "how_to_solve": "OneClickAPI uses a backend proxy to eliminate CORS issues instantly." },
  { "keyword": "test webhook url without registration", "slug": "test-webhook-no-registration", "title": "Test Webhooks & API Endpoints Online - No Signup Required", "problem_description": "User wants to verify a JSON endpoint but won't give email to another SaaS.", "how_to_solve": "OneClickAPI is registration-free. Open, paste, and see results." },
  { "keyword": "generate fetch code from api url online", "slug": "generate-fetch-code-online", "title": "Convert API URL to JS Fetch Snippet in 1 Second", "problem_description": "Writing fetch boilerplate with headers is repetitive.", "how_to_solve": "OneClickAPI generates production-ready JS Fetch snippets instantly." },
  { "keyword": "insomnia alternative no account 2026", "slug": "insomnia-alternative-no-account", "title": "Looking for an Insomnia Alternative? Try No-Account OneClickAPI", "problem_description": "Even Insomnia started pushing cloud accounts. Users want local-first simplicity.", "how_to_solve": "OneClickAPI provides a stateless testing environment with no sync." },
  { "keyword": "simple api debugger for non-developers", "slug": "simple-api-debugger-for-non-devs", "title": "Non-Dev Friendly API Tester - Just Paste the URL", "problem_description": "PMs need to check API status but find Postman UI too intimidating.", "how_to_solve": "The 'Paste & Go' interface makes it accessible for anyone." },
  { "keyword": "why is postman so slow 2026", "slug": "postman-slow-alternative", "title": "Postman is Slow? Switch to a 0.8s API Testing Tool", "problem_description": "Frustrated with Electron-based heavy UI of traditional clients.", "how_to_solve": "OneClickAPI is built for speed. Minimal JS, raw execution." },
  { "keyword": "debug json api headers online", "slug": "debug-json-api-headers", "title": "See All API Response Headers Online - Instant View", "problem_description": "Need to check 'x-cache' or 'set-cookie' without browser dev tools.", "how_to_solve": "OneClickAPI displays both body and all response headers clearly." },
  { "keyword": "test public api with api key online", "slug": "test-public-api-key-online", "title": "Quickly Test Public APIs with API Keys - Secure & Fast", "problem_description": "User wants to test a Google API key without setting up a project.", "how_to_solve": "Simple header inputs allow quick 'Authorization' key testing." },
  { "keyword": "lightweight postman web version", "slug": "lightweight-postman-web", "title": "The Lightweight Web Alternative to Postman (No Install)", "problem_description": "User on restricted machine cannot install desktop apps.", "how_to_solve": "OneClickAPI is 100% web-based and requires zero installation." },
  { "keyword": "format json response from api call online", "slug": "format-api-json-online", "title": "Auto-Format & Beautify API JSON Responses Online", "problem_description": "APIs return minified JSON which is impossible to read in a raw tab.", "how_to_solve": "OneClickAPI automatically beautifies and highlights JSON syntax." },
  { "keyword": "copy api response as json file", "slug": "copy-api-response-json", "title": "Download or Copy API Response in One Click", "problem_description": "User needs API data for a mock file but manual copying is error-prone.", "how_to_solve": "A dedicated 'Copy JSON' button captures the entire response instantly." },
  { "keyword": "test bearer token api online", "slug": "test-bearer-token-online", "title": "Instant Bearer Token API Testing - Paste & Run", "problem_description": "Confusing UI in other tools makes adding 'Bearer' prefix a chore.", "how_to_solve": "Intuitive header input makes auth testing a 2-second task." },
  { "keyword": "online rest client for quick debugging", "slug": "online-rest-client-quick-debug", "title": "Minimalist Online REST Client for Zero-Latency Debugging", "problem_description": "Generic 'REST Clients' are often old, ugly, or filled with ads.", "how_to_solve": "OneClickAPI is a modern, clean, ad-free experience for devs." },
  { "keyword": "share api test result link", "slug": "share-api-result-link", "title": "Share Your API Response with Team (No Signup)", "problem_description": "User wants to show a co-worker exactly what an API is returning.", "how_to_solve": "Stateless nature means we focus on quick debugging and visualization." },
  { "keyword": "convert url to python script instantly", "slug": "convert-url-to-python", "title": "Turn any API URL into a Python Script - No Manual Coding", "problem_description": "Beginners struggle with how to use 'requests' library correctly.", "how_to_solve": "OneClickAPI provides full boilerplate code including imports." },
  { "keyword": "test https api from http site", "slug": "test-https-from-http", "title": "Bridge the Gap: Test HTTPS APIs without Mixed Content Errors", "problem_description": "Browser security prevents testing endpoints due to protocol mismatch.", "how_to_solve": "Server-side proxy bypasses protocol-related browser blocks." },
  { "keyword": "minimalist api tester for chromebook", "slug": "api-tester-for-chromebook", "title": "The Best API Testing Tool for Chromebook Developers", "problem_description": "Chromebooks can't run native desktop API clients easily.", "how_to_solve": "High-performance web interface is perfect for cloud-based dev." },
  { "keyword": "convert curl to axios online 2026", "slug": "convert-curl-to-axios", "title": "Instant cURL to Axios Converter - Clean & Modern Syntax", "problem_description": "Copying from DevTools and rewriting to Axios is a waste of time.", "how_to_solve": "Paste cURL, click Axios tab, get copy-pasteable snippet." },
  { "keyword": "generate node-fetch code from endpoint", "slug": "generate-node-fetch-from-url", "title": "One-Click Node-Fetch Code Generator for Backend Devs", "problem_description": "Writing Node.js server requests often requires specific header formatting.", "how_to_solve": "OneClickAPI formats everything into a perfect Node-Fetch template." },
  { "keyword": "api to go struct converter online", "slug": "api-to-go-struct-converter", "title": "Test API & Generate Golang Structs in One Go", "problem_description": "Gophers need to map JSON to structs, usually requires a separate tool.", "how_to_solve": "Get JSON response and 'Copy as Go Struct' in one interface." },
  { "keyword": "curl to php curl_init generator", "slug": "curl-to-php-generator", "title": "Quick cURL to PHP Code Generator - No More Manual Array Setup", "problem_description": "PHP's curl_setopt arrays are notoriously verbose.", "how_to_solve": "OneClickAPI generates the full PHP boilerplate instantly." },
  { "keyword": "api response to typescript interface online", "slug": "api-response-to-typescript-interface", "title": "Turn API JSON into TypeScript Interfaces Automatically", "problem_description": "Manual type definition for complex JSON is the #1 productivity killer.", "how_to_solve": "Hit 'Copy as TS Interface' and paste directly into your project." },
  { "keyword": "test localhost api from another device", "slug": "test-localhost-api", "title": "Test Localhost APIs without Ngrok (OneClick Proxy)", "problem_description": "Quickly check if an API works without setting up a tunnel.", "how_to_solve": "Proxy acts as a bridge for testing reachable public or local endpoints." },
  { "keyword": "debug set-cookie header api online", "slug": "debug-set-cookie-header", "title": "Inspect 'Set-Cookie' Headers - Hidden by Browsers, Visible Here", "problem_description": "Fetch API hides sensitive headers due to security policies.", "how_to_solve": "Our backend proxy captures everything, showing the true raw response." },
  { "keyword": "fix cors preflight error during testing", "slug": "fix-cors-preflight-api", "title": "Bypass CORS Preflight Issues with OneClickAPI Proxy", "problem_description": "OPTIONS requests failing in browser stop testing of GET/POST logic.", "how_to_solve": "Routing through proxy handles preflight, showing final response data." },
  { "keyword": "check api latency from different regions", "slug": "check-api-latency-online", "title": "Measure API Response Time (TTFB) Instantly Online", "problem_description": "Is the API slow or is it your network? Users need a baseline.", "how_to_solve": "OneClickAPI reports execution time from high-speed server to target." },
  { "keyword": "test rest api with custom user agent", "slug": "test-api-custom-user-agent", "title": "Send Custom User-Agent Headers Without Browser Plugins", "problem_description": "Some APIs block requests that don't look like a specific browser.", "how_to_solve": "Add 'User-Agent' header easily to spoof any device for testing." },
  { "keyword": "test rest api on ipad browser 2026", "slug": "test-api-on-ipad", "title": "The Best API Testing Tool for iPad Pro Workflows", "problem_description": "iPadOS lacks a professional-grade Postman that isn't a toy.", "how_to_solve": "Responsive web UI turns tablet into a powerful debugging station." },
  { "keyword": "api tester for restricted work laptops", "slug": "api-tester-restricted-laptop", "title": "Can't Install Apps? Use this Online API Client on Work PC", "problem_description": "Corporate IT policies often block .exe or .dmg installs.", "how_to_solve": "OneClickAPI requires zero installation, works in any browser." },
  { "keyword": "send post request from mobile phone browser", "slug": "send-post-request-mobile", "title": "How to Send POST Requests from Your Phone (Simple & Fast)", "problem_description": "Testing a POST endpoint on mobile is nearly impossible with dev tools.", "how_to_solve": "Mobile-optimized form makes it easy to type JSON and hit Send." },
  { "keyword": "lightweight swagger ui alternative online", "slug": "lightweight-swagger-alternative", "title": "A Faster, Leaner Alternative to Heavy Swagger UI Pages", "problem_description": "Large Swagger files take forever to render and crash the tab.", "how_to_solve": "Forget the docs. If you know the endpoint, we are 10x faster." },
  { "keyword": "api client that doesn't track headers", "slug": "privacy-first-api-client", "title": "Private API Testing: No Tracking, No Logging of Keys", "problem_description": "Users wary of AI tools ingesting API keys into training sets.", "how_to_solve": "Stateless execution. Keys pass through memory, never written to DB." },
  { "keyword": "how to show api response in a blog post", "slug": "show-api-response-blog", "title": "Easily Demo API Responses with Clean Screenshots", "problem_description": "Bloggers need clean UI for screenshots without sidebars.", "how_to_solve": "Minimalist UI is 'Screenshot Ready'—no ads, just beautiful JSON." },
  { "keyword": "test graphql endpoint as rest", "slug": "test-graphql-as-rest", "title": "Quick GraphQL Query Tester - Just Paste the URL", "problem_description": "Simple GraphQL checks shouldn't require a full Playground setup.", "how_to_solve": "Paste endpoint and send query as POST body in OneClickAPI." },
  { "keyword": "validate json response schema online", "slug": "validate-json-schema-online", "title": "Instant JSON Schema Validation for API Responses", "problem_description": "Checking if API returns the right structure manually is slow.", "how_to_solve": "Visual JSON highlighting makes validation a breeze." },
  { "keyword": "online api tool for low bandwidth", "slug": "api-tool-low-bandwidth", "title": "Low Bandwidth API Testing Tool for Remote Areas", "problem_description": "Heavy apps fail on 3G or unstable hotel Wi-Fi.", "how_to_solve": "Minimal payload size works even when connection is crawling." },
  { "keyword": "alternative to rapidapi client", "slug": "rapidapi-client-alternative", "title": "A Faster Alternative to the RapidAPI Testing Tab", "problem_description": "RapidAPI interface can be sluggish and overloaded.", "how_to_solve": "Use OneClickAPI for raw, unfiltered testing speed." },
  { "keyword": "test basic auth api online instantly", "slug": "test-basic-auth-online", "title": "Simple Basic Auth API Tester - Just Username/Password", "problem_description": "Encoding Base64 for Basic Auth manually is annoying.", "how_to_solve": "Input credentials and we handle the 'Authorization' header encoding." },
  { "keyword": "api tester for raspberry pi chromium", "slug": "api-tester-raspberry-pi", "title": "Run API Tests on Raspberry Pi via Lightweight Web App", "problem_description": "Postman is too heavy for Pi; users need a browser solution.", "how_to_solve": "Low-resource web app is the perfect match for ARM-based dev." },
  { "keyword": "test webhooks free no credit card", "slug": "test-webhooks-free", "title": "Free Webhook & API Testing - No CC, No BS", "problem_description": "Tools asking for CC for 'pro' features are annoying.", "how_to_solve": "Everything you need is accessible in OneClickAPI for free." },
  { "keyword": "online curl formatter and executor", "slug": "curl-formatter-executor", "title": "Format and Execute cURL Commands Online Instantly", "problem_description": "Messy cURL strings are hard to read and debug.", "how_to_solve": "Paste it, let us format it, and see it run with one click." },
  { "keyword": "see raw http request sent by browser", "slug": "see-raw-http-request", "title": "Inspect Raw HTTP Requests Sent to Your Server", "problem_description": "Devs want to see exactly what's sent 'under the hood'.", "how_to_solve": "We display outgoing request structure clearly for debugging." },
  { "keyword": "test microservices api online fast", "slug": "test-microservices-online", "title": "Microservices API Debugger - Fast & Stateless", "problem_description": "Managing 20 Postman collections for 20 microservices is a nightmare.", "how_to_solve": "Just paste the specific endpoint you're working on and get it done." },
  { "keyword": "get status code of url online 2026", "slug": "get-url-status-code", "title": "Quickly Check HTTP Status Codes (200, 404, 500) Online", "problem_description": "User wants to know if a link is dead without using terminal.", "how_to_solve": "Color-coded badge shows status code in 0.8s." },
  { "keyword": "inspect api response time breakdown", "slug": "api-time-breakdown", "title": "Detailed API Response Time Breakdown Online", "problem_description": "Is it DNS or server processing that's slow?", "how_to_solve": "Timing breakdown provided for every request from proxy view." },
  { "keyword": "test oauth2 token endpoint online", "slug": "test-oauth2-online", "title": "Debug OAuth2 Token Endpoints Without Complexity", "problem_description": "Setting up OAuth2 in Postman requires a PhD in navigation.", "how_to_solve": "Send POST with credentials and see token response instantly." },
  { "keyword": "api client with dark mode 2026", "slug": "api-client-dark-mode", "title": "Modern API Client - Dark Mode for Eyesight Protection", "problem_description": "White screens at 2 AM kill developer productivity.", "how_to_solve": "Sleek, high-contrast dark mode as the core aesthetic." },
  { "keyword": "one click rest api test tool", "slug": "one-click-rest-test", "title": "The One-Click REST API Test - No Settings, Just Action", "problem_description": "Users are tired of 'Settings' menus. They just want a button.", "how_to_solve": "OneClickAPI lives up to its name: One click to result." },
  { "keyword": "is my api key working online check", "slug": "check-api-key-working", "title": "Verify if Your API Key is Working - Instant Check", "problem_description": "New devs want a quick way to see if they've configured keys right.", "how_to_solve": "Paste test endpoint and key to get immediate confirmation." },
  { "keyword": "convert json response to csv online", "slug": "json-to-csv-api", "title": "Convert API JSON Results to CSV for Excel Online", "problem_description": "Data analysts need to move API data into spreadsheets easily.", "how_to_solve": "View data and use our integrated export tools." },
  { "keyword": "test api with self-signed certificate", "slug": "test-self-signed-api", "title": "Test APIs with Self-Signed Certificates Online", "problem_description": "Browsers block dev APIs with self-signed certs.", "how_to_solve": "Proxy can be configured to allow insecure connections for dev." },
  { "keyword": "fix 415 unsupported media type error", "slug": "fix-415-error-online", "title": "Debug 415 Unsupported Media Type Errors Fast", "problem_description": "Devs forget 'Content-Type: application/json' and get frustrated.", "how_to_solve": "Tool suggests common content-type headers based on input." },
  { "keyword": "test api on non-standard ports", "slug": "test-api-custom-port", "title": "Test APIs on Ports 8080, 3000 Online", "problem_description": "Some online tools only allow port 80/443.", "how_to_solve": "Proxy supports any port, ideal for dev-server testing." },
  { "keyword": "why fetch returning 403 online fix", "slug": "debug-fetch-403", "title": "Debug 403 Forbidden Errors in Your Fetch Calls", "problem_description": "Devs get 403s because they lack User-Agents or headers.", "how_to_solve": "Mirror request to see what's missing compared to a working version." },
  { "keyword": "online tool to send patch request", "slug": "send-patch-request-online", "title": "Send HTTP PATCH Requests Online - Zero Config", "problem_description": "Some simple tools only support GET and POST.", "how_to_solve": "Full HTTP method support including PATCH, DELETE, and PUT." },
  { "keyword": "inspect x-request-id header online", "slug": "inspect-request-id", "title": "Track API Requests with X-Request-ID Header View", "problem_description": "Debugging microservices requires seeing tracing headers clearly.", "how_to_solve": "All headers, including custom ones, are displayed by default." },
  { "keyword": "test api without browser devtools", "slug": "test-api-no-devtools", "title": "Modern API Testing Without Opening Browser DevTools", "problem_description": "DevTools Network tab is cluttered with ads and analytics requests.", "how_to_solve": "Isolated environment for your API call and nothing else." },
  { "keyword": "generate axios boilerplate from url", "slug": "axios-boilerplate-generator", "title": "Generate Axios Boilerplate from URL - Copy & Paste", "problem_description": "Manually typing axios.post with configs is error-prone.", "how_to_solve": "OneClickAPI creates the full code block for you." },
  { "keyword": "test vercel serverless function online", "slug": "test-vercel-function", "title": "Test Vercel Serverless Functions Without Local Setup", "problem_description": "Need to check if a deployed lambda works before integrating.", "how_to_solve": "Paste the Vercel URL and see the execution result immediately." },
  { "keyword": "debug netlify function api endpoint", "slug": "debug-netlify-function", "title": "Debug Netlify Functions - Online Testing Tool", "problem_description": "Testing serverless functions shouldn't require CLI deployment.", "how_to_solve": "Hit your Netlify endpoint and debug responses in real-time." },
  { "keyword": "test nextjs api route online", "slug": "test-nextjs-api-route", "title": "Test Next.js API Routes Without Localhost Setup", "problem_description": "Vercel deployments need quick validation from the web.", "how_to_solve": "Direct testing of Next.js API endpoints with full header support." },
  { "keyword": "online tool for testing flask api", "slug": "test-flask-api-online", "title": "Test Flask REST APIs Online - Quick Python Backend Check", "problem_description": "Python developers need a quick way to verify Flask endpoints.", "how_to_solve": "Supports Flask's common patterns including JSON and form data." },
  { "keyword": "test express js api endpoint online", "slug": "test-express-api-online", "title": "Debug Express.js APIs - Node Backend Testing", "problem_description": "Node.js developers want to test Express routes quickly.", "how_to_solve": "Full support for Express middleware headers and JSON bodies." },
  { "keyword": "test ruby on rails api online", "slug": "test-rails-api-online", "title": "Instant Ruby on Rails API Tester - Test JSON Endpoints", "problem_description": "Checking Rails API responses shouldn't require 'rails console'.", "how_to_solve": "Direct endpoint testing with support for Rails-specific headers." },
  { "keyword": "how to test django rest framework api", "slug": "test-drf-api-online", "title": "Django REST Framework (DRF) Online Debugger", "problem_description": "Quickly verify DRF serializers and viewsets from the web.", "how_to_solve": "Full support for DRF's JSON responses and Auth tokens." },
  { "keyword": "test fastapi endpoint online instantly", "slug": "test-fastapi-online", "title": "FastAPI Online Tester - Validate Your Pydantic Models", "problem_description": "Verify if your FastAPI endpoint handles JSON bodies correctly.", "how_to_solve": "Input JSON and see if FastAPI returns 200 or 422 errors." },
  { "keyword": "check api compression gzip online", "slug": "check-api-gzip", "title": "Check if Your API is Gzipped - Inspect Encoding Headers", "problem_description": "User wants to verify if 'Content-Encoding: gzip' is active.", "how_to_solve": "We show raw headers so you can verify server-side compression." },
  { "keyword": "test api with custom content-type", "slug": "custom-content-type-api", "title": "Send API Requests with Custom Content-Type Headers", "problem_description": "Need to test 'application/xml' or 'text/csv' endpoints.", "how_to_solve": "Fully customizable Content-Type header support in the UI." },
  { "keyword": "test spring boot api online check", "slug": "test-spring-boot-api", "title": "Spring Boot REST API Online Tester - Instant JSON Check", "problem_description": "Java devs needing a quick way to test local/deployed controllers.", "how_to_solve": "Paste your Spring Boot endpoint and see the JSON mapping result." },
  { "keyword": "online tool to test put requests", "slug": "test-put-request-online", "title": "How to Send HTTP PUT Requests Online - Simple & Fast", "problem_description": "Updating data via API shouldn't be a complex task.", "how_to_solve": "Select PUT, add body, and hit Send. It's that simple." },
  { "keyword": "debug 502 bad gateway api online", "slug": "debug-502-api-error", "title": "Debug 502 Bad Gateway Errors in Your API Proxy", "problem_description": "Is it the load balancer or the app server failing?", "how_to_solve": "Our proxy gives a clean view of the 502 response from the source." },
  { "keyword": "test api with raw body online", "slug": "test-api-raw-body", "title": "Send Raw Body Requests (JSON, Text, XML) Online", "problem_description": "Some APIs expect raw text instead of structured JSON.", "how_to_solve": "Raw body input mode for maximum flexibility." },
  { "keyword": "how to test api with jwt token online", "slug": "test-jwt-token-online", "title": "Test APIs with JWT Tokens - Online Token Debugger", "problem_description": "Debugging JWT-secured endpoints requires proper header formatting.", "how_to_solve": "Easy Authorization header input with Bearer prefix support." },
  { "keyword": "check api rate limit headers online", "slug": "check-rate-limit-headers", "title": "Inspect API Rate Limit Headers (X-RateLimit-*) Online", "problem_description": "Developers need to see rate limit status to handle throttling.", "how_to_solve": "All X-RateLimit headers displayed clearly in response view." },
  { "keyword": "test api with query parameters online", "slug": "test-query-params-online", "title": "Test APIs with Query Parameters - URL Builder Online", "problem_description": "Building complex query strings manually is error-prone.", "how_to_solve": "Visual query parameter builder with automatic URL encoding." },
  { "keyword": "debug api redirect 301 302 online", "slug": "debug-redirects-online", "title": "Debug API Redirects (301, 302) - Follow or Inspect", "problem_description": "Understanding redirect chains is crucial for API debugging.", "how_to_solve": "Option to follow redirects or inspect each hop in the chain." },
  { "keyword": "test api with multipart form data", "slug": "test-multipart-form", "title": "Send Multipart/Form-Data Requests Online", "problem_description": "Testing file uploads requires proper multipart encoding.", "how_to_solve": "Built-in multipart form data support for file upload testing." },
  { "keyword": "compare api response times online", "slug": "compare-api-latency", "title": "Compare API Response Times - Benchmark Tool", "problem_description": "Need to compare latency between different endpoints or versions.", "how_to_solve": "Side-by-side comparison of response times from multiple APIs." },
  { "keyword": "test api with different http methods", "slug": "test-all-http-methods", "title": "Test All HTTP Methods (GET POST PUT DELETE PATCH)", "problem_description": "REST APIs use multiple methods, testing tools should support all.", "how_to_solve": "Full support for all standard HTTP methods in one interface." },
  { "keyword": "generate python requests code online", "slug": "generate-python-requests", "title": "Generate Python requests Code from API Call", "problem_description": "Converting API calls to Python scripts manually takes time.", "how_to_solve": "One-click generation of Python requests code with proper formatting." },
  { "keyword": "generate golang http code online", "slug": "generate-golang-http", "title": "Generate Go HTTP Client Code from API Endpoint", "problem_description": "Go developers need properly formatted http.Client code.", "how_to_solve": "Automatic generation of Go HTTP request code with error handling." },
  { "keyword": "generate rust reqwest code online", "slug": "generate-rust-reqwest", "title": "Generate Rust Reqwest Code from API Call", "problem_description": "Rust developers need type-safe HTTP client code.", "how_to_solve": "Generate Rust reqwest code with proper async/await patterns." },
  { "keyword": "test websocket connection online", "slug": "test-websocket-online", "title": "Test WebSocket Connections - Online WS Debugger", "problem_description": "WebSocket debugging requires specialized tools.", "how_to_solve": "Connect to WebSocket endpoints and send/receive messages." },
  { "keyword": "test sse server sent events online", "slug": "test-sse-online", "title": "Test Server-Sent Events (SSE) Endpoints Online", "problem_description": "Debugging SSE streams requires seeing events in real-time.", "how_to_solve": "Connect to SSE endpoints and display events as they arrive." },
  { "keyword": "validate api json response online", "slug": "validate-api-json", "title": "Validate API JSON Response Structure Online", "problem_description": "Ensuring API responses match expected schema is important.", "how_to_solve": "JSON validation against schema with detailed error reporting." },
  { "keyword": "pretty print api json response", "slug": "pretty-print-api-json", "title": "Pretty Print API JSON Responses - Online Formatter", "problem_description": "Minified JSON is hard to read and debug.", "how_to_solve": "Automatic JSON pretty-printing with syntax highlighting." },
  { "keyword": "test api with bearer auth online", "slug": "test-bearer-auth", "title": "Test APIs with Bearer Token Authentication Online", "problem_description": "Bearer token APIs require proper Authorization header formatting.", "how_to_solve": "Simple Bearer token input with automatic header formatting." },
  { "keyword": "test api with api key in header", "slug": "test-api-key-header", "title": "Test APIs with API Key in Header - Online Tool", "problem_description": "API keys in headers need proper key name and value formatting.", "how_to_solve": "Flexible header input for any API key naming convention." },
  { "keyword": "test api with api key in query", "slug": "test-api-key-query", "title": "Test APIs with API Key in Query Parameter", "problem_description": "Some APIs expect keys in query strings instead of headers.", "how_to_solve": "Query parameter builder with API key support." },
  { "keyword": "online postman alternative free", "slug": "postman-alternative-free", "title": "Free Postman Alternative - No Account Required", "problem_description": "Postman requires account and has become bloated over time.", "how_to_solve": "Free, lightweight alternative with zero registration needed." },
  { "keyword": "online api client for developers", "slug": "api-client-for-developers", "title": "API Client Built for Developers - By Developers", "problem_description": "Existing tools have become too complex for simple tasks.", "how_to_solve": "Developer-first design focusing on speed and simplicity." },
  { "keyword": "test api endpoint online free tool", "slug": "test-api-endpoint-free", "title": "Free API Endpoint Testing Tool - Online & Instant", "problem_description": "Developers need a quick way to test endpoints without setup.", "how_to_solve": "Instant testing with no installation or registration required." },
  { "keyword": "api testing tool for beginners", "slug": "api-testing-beginners", "title": "API Testing Tool for Beginners - Learn by Doing", "problem_description": "New developers find existing API tools intimidating.", "how_to_solve": "Simple interface that teaches API concepts through practice." },
  { "keyword": "test rest api without coding", "slug": "test-rest-api-no-code", "title": "Test REST APIs Without Writing Code", "problem_description": "Non-developers need to test APIs without programming knowledge.", "how_to_solve": "Visual interface that requires zero coding skills." },
  { "keyword": "api debugger with syntax highlighting", "slug": "api-debugger-syntax", "title": "API Debugger with JSON Syntax Highlighting", "problem_description": "Plain text JSON responses are hard to read.", "how_to_solve": "Beautiful syntax highlighting for all JSON responses." },
  { "keyword": "test api with custom headers online", "slug": "test-custom-headers", "title": "Test APIs with Custom Headers - Online Tool", "problem_description": "APIs often require custom headers for authentication or versioning.", "how_to_solve": "Easy custom header input with common presets." },
  { "keyword": "test api response content type", "slug": "test-content-type", "title": "Test API Response Content-Type Headers", "problem_description": "Verifying Content-Type is crucial for API integration.", "how_to_solve": "Clear display of response Content-Type and encoding." },
  { "keyword": "debug api cors errors online", "slug": "debug-cors-errors", "title": "Debug CORS Errors - Online CORS Troubleshooter", "problem_description": "CORS errors are frustrating and hard to debug.", "how_to_solve": "Detailed CORS error reporting and solution suggestions." },
  { "keyword": "test api ssl certificate online", "slug": "test-ssl-certificate", "title": "Test API SSL/TLS Certificates Online", "problem_description": "SSL issues can cause API failures that are hard to diagnose.", "how_to_solve": "SSL certificate validation and expiration checking." },
  { "keyword": "check api health status online", "slug": "check-api-health", "title": "Check API Health Status - Online Monitoring", "problem_description": "Need to quickly check if an API is up and running.", "how_to_solve": "Health check endpoint with status code and response time." },
  { "keyword": "test graphql api online tool", "slug": "test-graphql-api", "title": "Test GraphQL APIs - Online GraphQL Client", "problem_description": "GraphQL testing requires specialized query and variable support.", "how_to_solve": "Full GraphQL support with query editor and variable input." },
  { "keyword": "convert curl to fetch javascript", "slug": "curl-to-fetch-js", "title": "Convert cURL to JavaScript Fetch - Online Converter", "problem_description": "Converting cURL commands to fetch code is tedious.", "how_to_solve": "Automatic conversion with proper header and body handling." },
  { "keyword": "convert curl to python requests", "slug": "curl-to-python", "title": "Convert cURL to Python Requests - Code Generator", "problem_description": "Python developers need requests library code from cURL.", "how_to_solve": "Generate Python requests code with session handling." },
  { "keyword": "api response time checker online", "slug": "api-response-time", "title": "API Response Time Checker - Measure Latency", "problem_description": "API performance is critical for user experience.", "how_to_solve": "Accurate response time measurement with multiple test runs." },
  { "keyword": "test api with timeout settings", "slug": "test-api-timeout", "title": "Test APIs with Custom Timeout Settings", "problem_description": "Slow APIs need configurable timeout handling.", "how_to_solve": "Custom timeout configuration for all API requests." },
  { "keyword": "test api with retry logic online", "slug": "test-api-retry", "title": "Test APIs with Automatic Retry Logic", "problem_description": "Unreliable APIs benefit from retry mechanisms.", "how_to_solve": "Built-in retry logic with configurable attempts and backoff." }
]
